client/__init__.py
client/client.py
client/client/__init__.py
client/client/add_contact.py
client/client/client_ui.py
client/client/database.py
client/client/del_contact.py
client/client/main_window.py
client/client/start_dialog.py
client/client/transport.py
client/common/__init__.py
client/common/decos.py
client/common/descriptors.py
client/common/errors.py
client/common/metaclasses.py
client/common/utils.py
client/common/variables.py
client/logs/__init__.py
client/logs/config_client_log.py
client/logs/config_server_log.py
client/unit_tests/__init__.py
client/unit_tests/test_client.py
client/unit_tests/test_utils.py
mrz_mess_client-0.0.1.dist-info/METADATA
mrz_mess_client-0.0.1.dist-info/WHEEL
mrz_mess_client-0.0.1.dist-info/top_level.txt
mrz_mess_client-0.0.1.dist-info/RECORD
